luminous.py
luminous-0.0.1.dist-info/LICENSE
luminous-0.0.1.dist-info/METADATA
luminous-0.0.1.dist-info/WHEEL
luminous-0.0.1.dist-info/top_level.txt
luminous-0.0.1.dist-info/RECORD
