Metadata-Version: 2.1
Name: luminous
Version: 0.0.1
Summary: Compute irradiance, spectral/absolute power, energy, illuminance, luminous intensity/flux, photon flux, as well as algorithms for splicing, cropping, peak-finding, FWHM, and box-car smoothing spectral objects.
Author-email: Phillip Curtsmith <phillip.curtsmith@gmail.com>
Project-URL: Homepage, https://pypi.org/project/luminous/
Project-URL: Bug Tracker, https://github.com/indigo-pc/luminous/issues
Classifier: Programming Language :: Python :: 3
Classifier: License :: OSI Approved :: GNU General Public License v3 (GPLv3)
Classifier: Operating System :: OS Independent
Classifier: Development Status :: 3 - Alpha
Classifier: Intended Audience :: Developers
Classifier: Intended Audience :: Education
Classifier: Intended Audience :: End Users/Desktop
Classifier: Intended Audience :: Science/Research
Classifier: Natural Language :: English
License-File: LICENSE
